uboxadmin/__init__.py
uboxadmin/apps.py
uboxadmin/authentication.py
uboxadmin/cool/__init__.py
uboxadmin/cool/signals.py
uboxadmin/cool/upsert.py
uboxadmin/decorators.py
uboxadmin/defines.py
uboxadmin/exceptions.py
uboxadmin/filters.py
uboxadmin/generic.py
uboxadmin/jwt/__init__.py
uboxadmin/jwt/compat.py
uboxadmin/jwt/serializers.py
uboxadmin/jwt/viewsets.py
uboxadmin/management/__init__.py
uboxadmin/management/commands/__init__.py
uboxadmin/management/commands/createuboxsuperuser.py
uboxadmin/management/commands/inituboxadmindb.py
uboxadmin/migrations/0001_initial.py
uboxadmin/migrations/0002_auto_20210521_1034.py
uboxadmin/migrations/0003_auto_20210601_1754.py
uboxadmin/migrations/0004_user_email.py
uboxadmin/migrations/0005_auto_20210622_1638.py
uboxadmin/migrations/0006_auto_20210622_1641.py
uboxadmin/migrations/0007_auto_20210625_0905.py
uboxadmin/migrations/__init__.py
uboxadmin/models/__init__.py
uboxadmin/models/base.py
uboxadmin/models/jwt.py
uboxadmin/models/space.py
uboxadmin/models/system.py
uboxadmin/pagination.py
uboxadmin/serializers.py
uboxadmin/settings.py
uboxadmin/test.py
uboxadmin/urls.py
uboxadmin/utils.py
uboxadmin/view_conf.py
uboxadmin/views/__init__.py
uboxadmin/views/base/__init__.py
uboxadmin/views/base/comm.py
uboxadmin/views/base/open.py
uboxadmin/views/base/plugin/info.py
uboxadmin/views/base/sys/__init__.py
uboxadmin/views/base/sys/department.py
uboxadmin/views/base/sys/log.py
uboxadmin/views/base/sys/param.py
uboxadmin/views/base/sys/role.py
uboxadmin/views/base/sys/urls.py
uboxadmin/views/base/sys/user.py
uboxadmin/views/base/urls.py
uboxadmin/views/django_apps.py
uboxadmin/views/space/__init__.py
uboxadmin/views/space/urls.py
uboxadmin/views/urls.py
uboxadmin-0.1.0.dist-info/WHEEL
uboxadmin-0.1.0.dist-info/METADATA
uboxadmin-0.1.0.dist-info/RECORD
